animation/__init__.py
chat/__init__.py
download/__init__.py
emotion/__init__.py
entity/__init__.py
face/__init__.py
fake/__init__.py
intro/__init__.py
keyboard/__init__.py
knowledge/__init__.py
language/__init__.py
messaging/__init__.py
news/__init__.py
objectron/__init__.py
scrape/__init__.py
selfie/__ini__.py
sentiment/__init__.py
setup/__init__.py
stream/__init__.py
transcribe/__init__.py
translate/__init__.py
voice/__init__.py
volume/__init__.py
webcam/__init__.py
webcam2/__init__.py
webcam3/__init__.py
aij-1.2.10.dist-info/LICENSE.txt
aij-1.2.10.dist-info/METADATA
aij-1.2.10.dist-info/WHEEL
aij-1.2.10.dist-info/entry_points.txt
aij-1.2.10.dist-info/top_level.txt
aij-1.2.10.dist-info/RECORD
