Metadata-Version: 2.1
Name: aij
Version: 1.2.10
Summary: AI Journalist
Author-email: Yilmaz Mustafa <dev@mail.be>
License: Copyright (c) 2016 The Python Packaging Authority (PyPA)
Project-URL: Homepage, https://www.codesapien.be/aij/
Project-URL: Bug Reports, https://github.com/codesapienbe/aij/issues
Project-URL: Funding, https://donate.pypi.org
Project-URL: Say Thanks!, http://saythanks.io/to/aij
Project-URL: Source, https://github.com/codesapienbe/aij
Keywords: aij,setuptools,development,ai journalist,machine learning,artificial intelligence
Classifier: Development Status :: 3 - Alpha
Classifier: Intended Audience :: Developers
Classifier: Topic :: Software Development :: Build Tools
Classifier: License :: OSI Approved :: MIT License
Classifier: Programming Language :: Python :: 3.9
Classifier: Programming Language :: Python :: 3.10
Classifier: Programming Language :: Python :: 3.11
Classifier: Programming Language :: Python :: 3 :: Only
Requires-Python: >=3.9
License-File: LICENSE.txt
Requires-Dist: requests
Requires-Dist: setuptools
Requires-Dist: wheel
Requires-Dist: pipenv
Requires-Dist: pylint
Requires-Dist: autopep8
Requires-Dist: pyinstaller
Requires-Dist: black
Requires-Dist: coveralls
Requires-Dist: coverage
Requires-Dist: flake8
Requires-Dist: mypy
Requires-Dist: pep8-naming
Requires-Dist: pre-commit
Requires-Dist: pytest
Requires-Dist: pytest-cov
Requires-Dist: pytest-mock
Requires-Dist: pytest-profiling
Requires-Dist: opencv-python
Requires-Dist: mediapipe
Requires-Dist: pandas
Requires-Dist: gtts
Requires-Dist: pygame
Requires-Dist: cairosvg
Requires-Dist: pika
Requires-Dist: newsapi-python
Requires-Dist: openai
Requires-Dist: openai-whisper
Requires-Dist: langchain
Requires-Dist: plyer
Requires-Dist: python-dotenv
Requires-Dist: kivy[dev]
Requires-Dist: docker
Requires-Dist: youtube-dl
Requires-Dist: python-ffmpeg
Requires-Dist: psutil
Requires-Dist: flask
Requires-Dist: flask-socketio
Requires-Dist: flask-cors
Requires-Dist: flask-sqlalchemy
Requires-Dist: deepface
Requires-Dist: speechbrain
Requires-Dist: soundfile
Requires-Dist: transformers
Requires-Dist: pytube3
Requires-Dist: nltk
Requires-Dist: spacy
Requires-Dist: jupyter
Requires-Dist: jupyterlab
Requires-Dist: jupyterlab-code-formatter
Requires-Dist: jupyterlab-git
Requires-Dist: jupyterlab-lsp
Requires-Dist: pynput
Requires-Dist: comtypes
Requires-Dist: pycaw
Requires-Dist: scipy
Requires-Dist: scikit-learn
Requires-Dist: tensorflow
Requires-Dist: numpy
Requires-Dist: matplotlib
Requires-Dist: seaborn
Provides-Extra: dev
Requires-Dist: check-manifest ; extra == 'dev'
Provides-Extra: test
Requires-Dist: coverage ; extra == 'test'
